setup.cfg
setup.py
migrator/__init__.py
migrator.egg-info/PKG-INFO
migrator.egg-info/SOURCES.txt
migrator.egg-info/dependency_links.txt
migrator.egg-info/entry_points.txt
migrator.egg-info/requires.txt
migrator.egg-info/top_level.txt