Metadata-Version: 1.1
Name: migrator
Version: 0.0.8
Summary: Database Migration Assistant
Home-page: https://github.com/lgastako/migrate
Author: John Evans
Author-email: lgastako@gmail.com
License: MIT
Platform: UNKNOWN
Provides: migrator
